CourseZero/DataHandlingTools.py
CourseZero/DataStorageTools.py
CourseZero/Errors.py
CourseZero/FileSystemTools.py
CourseZero/RequestTools.py
CourseZero/Store.py
CourseZero/UI.py
CourseZero/UrlMakers.py
CourseZero/__init__.py
CourseZero/environment.py
CourseZero/test_dataStore.py
CourseZero/Widgets/CampusAndProfIdentifiers.py
CourseZero/Widgets/Inputs.py
CourseZero/Widgets/TakedownInputs.py
CourseZero/Widgets/__init__.py
Notebooks/__init__.py
CourseZero-0.0.8.dist-info/METADATA
CourseZero-0.0.8.dist-info/WHEEL
CourseZero-0.0.8.dist-info/top_level.txt
CourseZero-0.0.8.dist-info/RECORD
