Metadata-Version: 2.1
Name: CourseZero
Version: 0.0.8
Summary: Tools for finding what may have been stolen from teachers.
Home-page: https://github.com/HatakoHaterson/CourseZero
Author: hatakohaterson
Author-email: hatako.haterson@gmail.com
License: MIT
Platform: UNKNOWN
Classifier: License :: OSI Approved :: MIT License
Classifier: Programming Language :: Python
Classifier: Programming Language :: Python :: 3
Classifier: Programming Language :: Python :: 3.6
Classifier: Programming Language :: Python :: Implementation :: CPython
Classifier: Programming Language :: Python :: Implementation :: PyPy
Requires-Python: >=3.6.0
Requires-Dist: requests
Requires-Dist: IPython
Requires-Dist: ipywidgets
Requires-Dist: pandas
Requires-Dist: bs4
